setup.py
trashcaron/__init__.py
trashcaron/trashcaron.py
trashcaron.egg-info/PKG-INFO
trashcaron.egg-info/SOURCES.txt
trashcaron.egg-info/dependency_links.txt
trashcaron.egg-info/entry_points.txt
trashcaron.egg-info/top_level.txt