Metadata-Version: 1.0
Name: trashcaron
Version: 0.1.6
Summary: Trashbin script with btrfs support and automatic trash purge feature.
Home-page: https://github.com/eayin2/trashcaron
Author: eayin2
Author-email: eayin2 at gmail dot com
License: UNKNOWN
Platform: UNKNOWN
